aitest/__init__.py
aitest/config_manager.py
aitest/config_utils.py
aitest/main.py
aitester/__init__.py
aitester/config_manager.py
aitester/config_utils.py
aitester/main.py
aitester-0.2.dist-info/METADATA
aitester-0.2.dist-info/WHEEL
aitester-0.2.dist-info/entry_points.txt
aitester-0.2.dist-info/top_level.txt
aitester-0.2.dist-info/RECORD
