Metadata-Version: 2.1
Name: aitester
Version: 0.2
Summary: UNKNOWN
Home-page: UNKNOWN
License: UNKNOWN
Platform: UNKNOWN
Requires-Dist: click
Requires-Dist: gitpython
Requires-Dist: openai
